AUTHORS
LICENSE
MANIFEST.in
README.rst
requirements.txt
setup.py
dnsimple_zoneimport/__init__.py
dnsimple_zoneimport/importer.py
dnsimple_zoneimport/meta.py
dnsimple_zoneimport/test_importer.py
dnsimple_zoneimport.egg-info/PKG-INFO
dnsimple_zoneimport.egg-info/SOURCES.txt
dnsimple_zoneimport.egg-info/dependency_links.txt
dnsimple_zoneimport.egg-info/entry_points.txt
dnsimple_zoneimport.egg-info/not-zip-safe
dnsimple_zoneimport.egg-info/requires.txt
dnsimple_zoneimport.egg-info/top_level.txt