Metadata-Version: 1.1
Name: dnsimple-zoneimport
Version: 0.1.1
Summary: A script that allows you to import a Bind zone file into your DNSimple account.
Home-page: https://github.com/wbrp/dnsimple-zoneimport
Author: Webrepublic AG
Author-email: tech@webrepublic.ch
License: MIT
Keywords: dnsimple dns "zone files" bind import api
Platform: UNKNOWN
Classifier: Development Status :: 4 - Beta
Classifier: Environment :: Console
Classifier: License :: OSI Approved :: MIT License
Classifier: Natural Language :: English
Classifier: Operating System :: MacOS
Classifier: Operating System :: POSIX :: Linux
Classifier: Programming Language :: Python :: 2.7
Classifier: Topic :: Internet :: Name Service (DNS)
Classifier: Topic :: Terminals
